localstack_httpbin/__init__.py
localstack_httpbin/extension.py
localstack_httpbin/server.py
localstack_httpbin/vendor/__init__.py
localstack_httpbin/vendor/httpbin/__init__.py
localstack_httpbin/vendor/httpbin/core.py
localstack_httpbin/vendor/httpbin/filters.py
localstack_httpbin/vendor/httpbin/helpers.py
localstack_httpbin/vendor/httpbin/structures.py
localstack_httpbin/vendor/httpbin/utils.py
localstack_httpbin/vendor/httpbin/version.py
localstack_httpbin/vendor/httpbin/static/favicon.ico
localstack_httpbin/vendor/httpbin/templates/UTF-8-demo.txt
localstack_httpbin/vendor/httpbin/templates/footer.html
localstack_httpbin/vendor/httpbin/templates/forms-post.html
localstack_httpbin/vendor/httpbin/templates/httpbin.1.html
localstack_httpbin/vendor/httpbin/templates/index.html
localstack_httpbin/vendor/httpbin/templates/moby.html
localstack_httpbin/vendor/httpbin/templates/sample.xml
localstack_httpbin/vendor/httpbin/templates/trackingscripts.html
localstack_httpbin/vendor/httpbin/templates/flasgger/index.html
localstack_httpbin/vendor/httpbin/templates/images/jackal.jpg
localstack_httpbin/vendor/httpbin/templates/images/pig_icon.png
localstack_httpbin/vendor/httpbin/templates/images/svg_logo.svg
localstack_httpbin/vendor/httpbin/templates/images/wolf_1.webp
localstack_extension_httpbin-0.1.2.dist-info/METADATA
localstack_extension_httpbin-0.1.2.dist-info/WHEEL
localstack_extension_httpbin-0.1.2.dist-info/entry_points.txt
localstack_extension_httpbin-0.1.2.dist-info/top_level.txt
localstack_extension_httpbin-0.1.2.dist-info/RECORD
