Metadata-Version: 2.1
Name: localstack-extension-httpbin
Version: 0.1.2
Summary: LocalStack Extension: httpbin
Home-page: https://github.com/localstack/localstack-extensions/tree/main/httpbin
Author: LocalStack
Author-email: info@localstack.cloud
Requires-Dist: Flask
Requires-Dist: MarkupSafe
Requires-Dist: decorator
Requires-Dist: itsdangerous
Requires-Dist: brotlipy
Requires-Dist: raven[flask]
Requires-Dist: gevent
Requires-Dist: flasgger
Provides-Extra: dev
Requires-Dist: localstack-core >=2.2 ; extra == 'dev'
